pymcr/__init__.py
pymcr/_version.py
pymcr/condition.py
pymcr/constraints.py
pymcr/mcr.py
pymcr/metrics.py
pymcr/regressors.py
pymcr/tests/__init__.py
pymcr/tests/test_condition.py
pymcr/tests/test_constraints.py
pymcr/tests/test_external_regressors.py
pymcr/tests/test_mcr.py
pymcr/tests/test_mcr_sklearn_like.py
pymcr/tests/test_metrics.py
pymcr/tests/test_regressors.py
pyMCR-0.5.1.dist-info/LICENSE.md
pyMCR-0.5.1.dist-info/METADATA
pyMCR-0.5.1.dist-info/WHEEL
pyMCR-0.5.1.dist-info/top_level.txt
pyMCR-0.5.1.dist-info/RECORD
